.DS_Store
DeltaPI/__init__.py
DeltaPI/AutoDiff/All_derivatives.py
DeltaPI/AutoDiff/AutoDiff.py
DeltaPI/AutoDiff/__init__.py
DeltaPI/AutoDiff/AutoDiff_Tests/__init__.py
DeltaPI/AutoDiff/AutoDiff_Tests/test_All_derivatives.py
DeltaPI/AutoDiff/AutoDiff_Tests/test_AutoDiff.py
DeltaPI/Extension/DeltaHedgePi.py
DeltaPI/Extension/__init__.py
DeltaPI_FantasticFour-1.0.0.dist-info/LICENSE
DeltaPI_FantasticFour-1.0.0.dist-info/METADATA
DeltaPI_FantasticFour-1.0.0.dist-info/WHEEL
DeltaPI_FantasticFour-1.0.0.dist-info/top_level.txt
DeltaPI_FantasticFour-1.0.0.dist-info/RECORD
