Metadata-Version: 2.1
Name: DeltaPI-FantasticFour
Version: 1.0.0
Summary: DeltaPI Package for CS207
Home-page: https://github.com/IACS-CS-207-FantasticFour/cs207-FinalProject
Author: Anna Davydova, Dan Cox, Valentina Toll Villagra, Stephen Moon
Author-email: stephenmoon@college.harvard.edu
License: UNKNOWN
Platform: UNKNOWN
Classifier: Programming Language :: Python :: 3
Classifier: License :: OSI Approved :: MIT License
Classifier: Operating System :: OS Independent
Requires-Python: >=3.6
